karpet/__init__.py
karpet/core.py
karpet/utils.py
karpet-0.5.2.dist-info/LICENSE
karpet-0.5.2.dist-info/METADATA
karpet-0.5.2.dist-info/WHEEL
karpet-0.5.2.dist-info/RECORD
