Metadata-Version: 2.3
Name: karpet
Version: 0.5.2
Summary: Library for fetching coin/token historical data, trends and more.
Author: n1
Author-email: hrdina.pavel@gmail.com
Requires-Python: ~=3.13
Classifier: Programming Language :: Python :: 3.13
Classifier: License :: OSI Approved :: MIT License
Classifier: Programming Language :: Python :: 3 :: Only
Classifier: Intended Audience :: Developers
Classifier: Topic :: Software Development :: Libraries
Provides-Extra: google
Requires-Dist: BeautifulSoup4 (>=4.13.3,<5)
Requires-Dist: aiohttp (>=3.11.12,<4)
Requires-Dist: cloudscraper (>=1.2.71,<2)
Requires-Dist: lxml (>=5.3.0,<6)
Requires-Dist: pandas (>=2.2,<3.0)
Requires-Dist: pytrends (>=4.9.2,<5) ; extra == "google"
Requires-Dist: requests (>=2.32.3,<3)
Project-URL: Homepage, https://github.com/im-n1/karpet
